imhotep_pmd/__init__.py
imhotep_pmd/plugin.py
imhotep_pmd-0.0.6.dist-info/entry_points.txt
imhotep_pmd-0.0.6.dist-info/LICENSE
imhotep_pmd-0.0.6.dist-info/WHEEL
imhotep_pmd-0.0.6.dist-info/METADATA
imhotep_pmd-0.0.6.dist-info/RECORD
