Metadata-Version: 2.1
Name: imhotep-pmd
Version: 0.0.6
Summary: An Imhotep plugin for PMD, the static analyzer.
License: MIT
Author: Mingyang Li
Author-email: imhotep_pmd@myli.page
Requires-Python: >=3.10,<4.0
Classifier: License :: OSI Approved :: MIT License
Classifier: Programming Language :: Python :: 3
Classifier: Programming Language :: Python :: 3.10
Requires-Dist: imhotep (>=2.0.0,<3.0.0)
Requires-Dist: jsonschema (>=4.4.0,<5.0.0)
Requires-Dist: requests (>=2.27.1,<3.0.0)
Requires-Dist: toml (>=0.10.2,<0.11.0)
